vsp_model_insight_influxdb/__init__.py
vsp_model_insight_influxdb/common/__init__.py
vsp_model_insight_influxdb/common/protocol.py
vsp_model_insight_influxdb/common/schedule.py
vsp_model_insight_influxdb/influxdb/__init__.py
vsp_model_insight_influxdb-0.1.0.dist-info/METADATA
vsp_model_insight_influxdb-0.1.0.dist-info/WHEEL
vsp_model_insight_influxdb-0.1.0.dist-info/namespace_packages.txt
vsp_model_insight_influxdb-0.1.0.dist-info/top_level.txt
vsp_model_insight_influxdb-0.1.0.dist-info/RECORD
