Metadata-Version: 2.1
Name: vsp-model-insight-influxdb
Version: 0.1.0
Summary: Model Performance Metrics Monitor Exporter
Home-page: https://pypi.org/project/vsp-model-insight-influxdb/
Author: he ke zhang
Author-email: yxzhk@hotmail.com
License: Apache-2.0
Classifier: Intended Audience :: End Users/Desktop
Classifier: Development Status :: 5 - Production/Stable
Classifier: Intended Audience :: End Users/Desktop
Classifier: License :: OSI Approved :: Apache Software License
Classifier: Programming Language :: Python
Classifier: Programming Language :: Python :: 3
Classifier: Programming Language :: Python :: 3.4
Classifier: Programming Language :: Python :: 3.5
Classifier: Programming Language :: Python :: 3.6
Classifier: Programming Language :: Python :: 3.7
Classifier: Programming Language :: Python :: 3.8
Classifier: Programming Language :: Python :: 3.9
Classifier: Programming Language :: Python :: 3.10
Requires-Dist: influxdb-client (>=1.36.1)
